waveforms/math/__init__.py
waveforms/math/_prime.cpython-311-darwin.so
waveforms/math/bayes.py
waveforms/math/fibheap.py
waveforms/math/func.py
waveforms/math/graph.py
waveforms/math/hmm.py
waveforms/math/interval.py
waveforms/math/paulis.py
waveforms/math/prime.py
waveforms/math/transmon.py
waveforms/math/version.py
waveforms/math/fit/__init__.py
waveforms/math/fit/_fit.py
waveforms/math/fit/delay.py
waveforms/math/fit/geo.py
waveforms/math/fit/peak.py
waveforms/math/fit/qubit_dynamics.py
waveforms/math/fit/readout.py
waveforms/math/fit/resonator.py
waveforms/math/fit/simple.py
waveforms/math/fit/spectrum.py
waveforms/math/fit/symmetry.py
waveforms/math/signal/__init__.py
waveforms/math/signal/demodulate.py
waveforms/math/signal/distortion.py
waveforms/math/signal/func.py
waveforms/quantum/__init__.py
waveforms/quantum/fourier_grid.py
waveforms/quantum/math.py
waveforms/quantum/rb.py
waveforms/quantum/tomo.py
waveforms/quantum/transmon.py
waveforms/quantum/xeb.py
waveforms/quantum/analyze/__init__.py
waveforms/quantum/analyze/coupling.py
waveforms/quantum/analyze/decoherence.py
waveforms/quantum/analyze/gate_error.py
waveforms/quantum/clifford/__init__.py
waveforms/quantum/clifford/clifford.py
waveforms/quantum/clifford/db.py
waveforms/quantum/clifford/mat.py
waveforms/quantum/clifford/seq2mat.py
waveforms_math-1.0.1.dist-info/LICENSE
waveforms_math-1.0.1.dist-info/METADATA
waveforms_math-1.0.1.dist-info/WHEEL
waveforms_math-1.0.1.dist-info/top_level.txt
waveforms_math-1.0.1.dist-info/RECORD
